ashitakhurana_101703115_missing_val/__init__.py
ashitakhurana_101703115_missing_val/missing_val.py
ashitakhuran_101703115_missing-0.0.1.dist-info/LICENSE.txt
ashitakhuran_101703115_missing-0.0.1.dist-info/METADATA
ashitakhuran_101703115_missing-0.0.1.dist-info/WHEEL
ashitakhuran_101703115_missing-0.0.1.dist-info/top_level.txt
ashitakhuran_101703115_missing-0.0.1.dist-info/RECORD
