Metadata-Version: 2.1
Name: ashitakhuran-101703115-missing
Version: 0.0.1
Summary: A small package that replaces missing values.
Home-page: UNKNOWN
Author: Ashita Khurana
Author-email: ashitakhurana99@gmail.com
License: UNKNOWN
Platform: UNKNOWN
Classifier: Programming Language :: Python :: 3
Classifier: License :: OSI Approved :: MIT License
Classifier: Operating System :: OS Independent
Requires-Python: >=3.6
